mkdocs_link_marker_plugin/__init__.py
mkdocs_link_marker_plugin/plugin.py
mkdocs_link_marker-0.1.3.dist-info/METADATA
mkdocs_link_marker-0.1.3.dist-info/WHEEL
mkdocs_link_marker-0.1.3.dist-info/entry_points.txt
mkdocs_link_marker-0.1.3.dist-info/top_level.txt
mkdocs_link_marker-0.1.3.dist-info/RECORD
