Metadata-Version: 2.1
Name: mkdocs-link-marker
Version: 0.1.3
Summary: MkDocs plugin for marking external or mail links in your documentation.
Home-page: https://github.com/timmeinerzhagen/mkdocs-link-marker
Author: Tim Jonas Meinerzhagen
Author-email: tim@meinerzhagen.me
License: MIT
Keywords: mkdocs link external
Classifier: Operating System :: OS Independent
Classifier: Programming Language :: Python
Classifier: Programming Language :: Python :: 3
Classifier: Programming Language :: Python :: 3.7
Classifier: Programming Language :: Python :: 3.8
Classifier: Programming Language :: Python :: 3.9
Classifier: Programming Language :: Python :: 3.10
Classifier: Programming Language :: Python :: 3 :: Only
Classifier: License :: OSI Approved :: MIT License
Classifier: Topic :: Documentation
Classifier: Topic :: Text Processing
Requires-Python: >=3.4
Requires-Dist: mkdocs >=1.0
Requires-Dist: jinja2
